.editorconfig
.gitignore
LICENSE
README.md
setup.cfg
setup.py
examples/twisted_tcp.py
uhf_reader/__init__.py
uhf_reader/constants.py
uhf_reader/exceptions.py
uhf_reader/factory.py
uhf_reader/packet.py
uhf_reader/protocol.py
uhf_reader/request.py
uhf_reader/response.py
uhf_reader/uhf_reader.py
uhf_reader.egg-info/PKG-INFO
uhf_reader.egg-info/SOURCES.txt
uhf_reader.egg-info/dependency_links.txt
uhf_reader.egg-info/top_level.txt