Metadata-Version: 1.1
Name: uhf-reader
Version: 0.2.7
Summary: Library to interface with Marktrace MR6100 series UHF RFID reader
Home-page: https://github.com/madprogrammer/mr6100-python
Author: Sergey Anufrienko
Author-email: serg@anufrienko.net
License: MIT
Platform: UNKNOWN
Classifier: Development Status :: 4 - Beta
Classifier: Intended Audience :: Developers
Classifier: Topic :: Software Development :: Libraries
Classifier: License :: OSI Approved :: MIT License
Classifier: Programming Language :: Python :: 3.5
Classifier: Programming Language :: Python :: 3.6
Classifier: Programming Language :: Python :: 3.7
